logit/__init__.py
logit/__main__.py
logit/_cli.py
logit/_common.py
logit/_data.py
logit/_enums.py
logit/_helper.py
logit/_logger.py
logit/_space.py
logit/_time.py
logit/output.py
logit/types_.py
logit_axis-0.1.5.dist-info/LICENSE
logit_axis-0.1.5.dist-info/METADATA
logit_axis-0.1.5.dist-info/WHEEL
logit_axis-0.1.5.dist-info/entry_points.txt
logit_axis-0.1.5.dist-info/top_level.txt
logit_axis-0.1.5.dist-info/RECORD
